ingate/__init__.py
ingate/ingatesdk.py
ingate/parser.py
ingatesdk-1.0.14.dist-info/LICENSE
ingatesdk-1.0.14.dist-info/METADATA
ingatesdk-1.0.14.dist-info/WHEEL
ingatesdk-1.0.14.dist-info/top_level.txt
ingatesdk-1.0.14.dist-info/RECORD
