Metadata-Version: 2.1
Name: ingatesdk
Version: 1.0.14
Summary: Ingate Python SDK
Home-page: https://github.com/ingatesystems/ingatesdk
Author: Ingate Systems AB
Author-email: fuegodev@ingate.com
License: UNKNOWN
Keywords: ingate,sdk,api
Platform: UNKNOWN
Classifier: Development Status :: 5 - Production/Stable
Classifier: Programming Language :: Python :: 2
Classifier: Programming Language :: Python :: 3
Classifier: License :: OSI Approved :: MIT License
Classifier: Intended Audience :: System Administrators
Classifier: Operating System :: OS Independent
Classifier: Topic :: Software Development :: Libraries :: Python Modules
